LICENSE
MANIFEST.in
README.rst
VERSION
requirements.txt
setup.py
src/kser_transport_kafka/__init__.py
src/kser_transport_kafka/consumer.py
src/kser_transport_kafka/producer.py
src/kser_transport_kafka.egg-info/PKG-INFO
src/kser_transport_kafka.egg-info/SOURCES.txt
src/kser_transport_kafka.egg-info/dependency_links.txt
src/kser_transport_kafka.egg-info/entry_points.txt
src/kser_transport_kafka.egg-info/requires.txt
src/kser_transport_kafka.egg-info/top_level.txt
src/kser_transport_kafka.egg-info/zip-safe