Metadata-Version: 1.1
Name: kser-transport-kafka
Version: 0.0.1
Summary: Kser librdkafka producer/consumer
Home-page: https://github.com/cdumay/kser-transport-kafka
Author: Cedric DUMAY
Author-email: cedric.dumay@gmail.com
License: MIT
Platform: UNKNOWN
Classifier: Programming Language :: Python
